codescholar/__init__.py
codescholar/cli.py
codescholar/metadata.py
codescholar/processor.py
codescholar/report.py
codescholar/rule.py
codescholar/aggregator/__init__.py
codescholar/aggregator/citation.py
codescholar/aggregator/code.py
codescholar/aggregator/community.py
codescholar/aggregator/documentation.py
codescholar/aggregator/license.py
codescholar/aggregator/metadata.py
codescholar/aggregator/packaging.py
codescholar/aggregator/repository.py
codescholar/aggregator/testing.py
codescholar/aggregator/version_control.py
codescholar/analyser/__init__.py
codescholar/analyser/changelog.py
codescholar/analyser/citation.py
codescholar/analyser/code.py
codescholar/analyser/code_markdown.py
codescholar/analyser/code_python.py
codescholar/analyser/conduct.py
codescholar/analyser/contributing.py
codescholar/analyser/dependecy_python.py
codescholar/analyser/documentation.py
codescholar/analyser/git.py
codescholar/analyser/jupyter_notebook.py
codescholar/analyser/license.py
codescholar/analyser/notice.py
codescholar/analyser/packaging_python.py
codescholar/analyser/testing_python.py
codescholar/analyser/data/licenses.json
codescholar/templates/issues.yaml
codescholar/templates/report.rst
codescholar-0.2.0.dist-info/METADATA
codescholar-0.2.0.dist-info/WHEEL
codescholar-0.2.0.dist-info/entry_points.txt
codescholar-0.2.0.dist-info/licenses/LICENSE
codescholar-0.2.0.dist-info/RECORD
