Metadata-Version: 2.4
Name: codescholar
Version: 0.2.0
Summary: A package and command-line utility to check code quality and compliance with best practices.
Project-URL: Homepage, https://github.com/SS-NES/codescholar
Project-URL: Issues, https://github.com/SS-NES/codescholar/issues
Author-email: Serkan Girgin <girgink@gmail.com>, Robert Ohuru <r.o.ohuru@utwente.nl>
License:                     GNU GENERAL PUBLIC LICENSE
License-File: LICENSE
Keywords: code quality,conformity assessment,software development
Classifier: Development Status :: 5 - Production/Stable
Classifier: Environment :: Console
Classifier: Intended Audience :: Developers
Classifier: Intended Audience :: Science/Research
Classifier: License :: OSI Approved :: GNU General Public License v3 (GPLv3)
Classifier: Operating System :: OS Independent
Classifier: Programming Language :: Python :: 3
Classifier: Programming Language :: Python :: 3.10
Classifier: Programming Language :: Python :: 3.11
Classifier: Programming Language :: Python :: 3.12
Classifier: Programming Language :: Python :: 3.13
Requires-Python: >=3.10
Requires-Dist: click<9,>=7.0
Requires-Dist: docstring-parser
Requires-Dist: gitpython
Requires-Dist: jinja2
Requires-Dist: pip-requirements-parser
Requires-Dist: pymarkdownlnt
Requires-Dist: pypandoc
Requires-Dist: pyyaml
